stackifyapm/__init__.py
stackifyapm/base.py
stackifyapm/decorators.py
stackifyapm/exceptions.py
stackifyapm/queue.py
stackifyapm/traces.py
stackifyapm/conf/__init__.py
stackifyapm/conf/constants.py
stackifyapm/context/__init__.py
stackifyapm/context/base.py
stackifyapm/context/contextvars.py
stackifyapm/context/threadlocal.py
stackifyapm/contrib/__init__.py
stackifyapm/contrib/aws_lambda/__init__.py
stackifyapm/contrib/aws_lambda/function.py
stackifyapm/contrib/azure_function/__init__.py
stackifyapm/contrib/celery/__init__.py
stackifyapm/contrib/django/__init__.py
stackifyapm/contrib/django/apps.py
stackifyapm/contrib/django/client.py
stackifyapm/contrib/django/context_processors.py
stackifyapm/contrib/django/handlers.py
stackifyapm/contrib/django/middleware/__init__.py
stackifyapm/contrib/flask/__init__.py
stackifyapm/contrib/flask/utils.py
stackifyapm/contrib/pyramid/__init__.py
stackifyapm/handlers/__init__.py
stackifyapm/handlers/exceptions.py
stackifyapm/instrumentation/__init__.py
stackifyapm/instrumentation/control.py
stackifyapm/instrumentation/decorators.py
stackifyapm/instrumentation/register.py
stackifyapm/instrumentation/packages/__init__.py
stackifyapm/instrumentation/packages/base.py
stackifyapm/instrumentation/packages/botocore.py
stackifyapm/instrumentation/packages/cassandra.py
stackifyapm/instrumentation/packages/custom.py
stackifyapm/instrumentation/packages/dbapi2.py
stackifyapm/instrumentation/packages/elasticsearch.py
stackifyapm/instrumentation/packages/jinja2.py
stackifyapm/instrumentation/packages/logger.py
stackifyapm/instrumentation/packages/mysql.py
stackifyapm/instrumentation/packages/psycopg2.py
stackifyapm/instrumentation/packages/pylibmc.py
stackifyapm/instrumentation/packages/pymongo.py
stackifyapm/instrumentation/packages/pymssql.py
stackifyapm/instrumentation/packages/pyodbc.py
stackifyapm/instrumentation/packages/python_memcached.py
stackifyapm/instrumentation/packages/redis.py
stackifyapm/instrumentation/packages/requests.py
stackify_python_apm-1.12.2.dist-info/LICENSE.md
stackify_python_apm-1.12.2.dist-info/METADATA
stackify_python_apm-1.12.2.dist-info/WHEEL
stackify_python_apm-1.12.2.dist-info/top_level.txt
stackify_python_apm-1.12.2.dist-info/zip-safe
stackify_python_apm-1.12.2.dist-info/RECORD
