Metadata-Version: 2.1
Name: stackify-python-apm
Version: 1.12.2
Summary: This is the official Python module for Stackify Python APM.
Home-page: https://www.stackify.com
Author: Stackify
Author-email: support@stackify.com
License: UNKNOWN
Platform: UNKNOWN
Classifier: Programming Language :: Python
Classifier: Programming Language :: Python :: 2.7
Classifier: Programming Language :: Python :: 3.4
Classifier: Programming Language :: Python :: 3.5
Classifier: Programming Language :: Python :: 3.6
Classifier: Programming Language :: Python :: 3.7
Classifier: Programming Language :: Python :: 3.8
Classifier: Programming Language :: Python :: Implementation :: CPython
Classifier: Programming Language :: Python :: Implementation :: PyPy
Classifier: Operating System :: OS Independent
License-File: LICENSE.md
Requires-Dist: blinker >=1.1
Requires-Dist: protobuf >=3.9.1
Requires-Dist: requests >=2.21.0
Requires-Dist: retrying >=1.2.3
Requires-Dist: stackify-api-python >=1.0.5
